Workbook

Sheet START HERE
A1: DEXTER E. BALBUENA | E-COMMERCE VA PORTFOLIO
A2: Excel case studies built around product research, listing quality, inventory tracking, and store operations.
A4: PURPOSE | B4: A practical portfolio workbook demonstrating spreadsheet workflows relevant to entry-level E-commerce VA work.
A5: PROJECT 1 — Product Research | B5: Compare sample products using price, rating, review count, estimated fees, and a simple opportunity score. Sample figures are fictional and for demonstration only.
A6: PROJECT 2 — Listing Quality Audit | B6: Audit listing titles, descriptions, images, SKU, category, and key attributes. Use the status column to prioritize cleanup.
A7: PROJECT 3 — Inventory & Reorder Tracker | B7: Monitor stock on hand, average daily sales, lead time, safety stock, reorder points, and suggested reorder quantities.
A8: PROJECT 4 — Order Operations Tracker | B8: Track sample orders by status, payment, fulfillment, and issue notes. Use filters to spot orders that may need follow-up.
A9: IMPORTANT PORTFOLIO NOTE | B9: These are simulated sample datasets, not real client results. Keep that transparent on your portfolio website. Replace the sample rows with anonymized or permission-approved data if you later work with clients.
A10: HOW TO USE | B10: Open each project tab, inspect formulas, filter the tables, and change sample inputs to see the workbook update. In Excel, formulas recalculate automatically.
A11: SUGGESTED PORTFOLIO TITLE | B11: E-commerce Operations Toolkit in Excel: Product Research, Listing Audit, Inventory Planning & Order Tracking
A12: WHAT THIS SHOWS | B12: Excel/Sheets organization, data cleaning, product comparison, operational tracking, basic formulas, conditional formatting, and clear documentation.

Sheet 5 Dashboard
A1: E-COMMERCE OPERATIONS | MINI DASHBOARD
A2: A quick summary of the fictional sample records across the workbook.
A4: Products researched | B4: =COUNTA('1 Product Research'!A4:A11)
A5: Listings needing review | B5: =COUNTIF('2 Listing Audit'!I4:I11,"Needs Review")+COUNTIF('2 Listing Audit'!I4:I11,"Needs Major Update")
A6: Inventory items to reorder | B6: =COUNTIF('3 Inventory Tracker'!J4:J11,"REORDER")
A7: Orders flagged for follow-up | B7: =COUNTIF('4 Order Tracker'!K4:K11,"FOLLOW UP")
A8: Estimated inventory value | B8: =SUM('3 Inventory Tracker'!L4:L11)
A9: Average sample product rating | B9: =AVERAGE('1 Product Research'!G4:G11)
A12: How to present this on your portfolio
A13: • Problem: Small online stores need accurate product data, clear listings, and visibility into inventory and order queues.
A14: • Approach: Built an Excel toolkit with structured tables, dropdowns, formulas, conditional formatting, and a summary dashboard.
A15: • Deliverables: Product comparison, listing audit, reorder tracker, order follow-up queue, and dashboard.
A16: • Transparency: Sample data is fictional. The workbook demonstrates process and spreadsheet skills, not actual client outcomes.

Sheet 1 Product Research
A1: PROJECT 1 | PRODUCT RESEARCH & COMPARISON
A2: Fictional sample data. Use this as a decision-support sheet, not as proof of actual profitability.
A3: Product | B3: Marketplace | C3: Category | D3: Selling Price (USD) | E3: Est. Cost (USD) | F3: Est. Platform/Referral Fee % | G3: Rating | H3: Review Count | I3: Est. Fee (USD) | J3: Est. Gross Margin (USD) | K3: Research Score | L3: Research Notes
A4: Adjustable Laptop Stand | B4: Amazon | C4: Desk Accessories | D4: 29.99 | E4: 12 | F4: 0.15 | G4: 4.5 | H4: 1840 | I4: =D4*F4 | J4: =D4-E4-I4 | K4: =ROUND((G4/5)*60+MIN(MAX(J4/D4,0),0.6)*40,0) | L4: Sample product; verify demand, competition, and current price.
A5: Under-Desk Headphone Hanger | B5: Amazon | C5: Desk Accessories | D5: 16.99 | E5: 5.5 | F5: 0.15 | G5: 4.4 | H5: 920 | I5: =D5*F5 | J5: =D5-E5-I5 | K5: =ROUND((G5/5)*60+MIN(MAX(J5/D5,0),0.6)*40,0) | L5: Sample product; check attachment compatibility and review themes.
A6: Cable Management Tray | B6: Shopee | C6: Office Organization | D6: 22.5 | E6: 8.25 | F6: 0.12 | G6: 4.3 | H6: 610 | I6: =D6*F6 | J6: =D6-E6-I6 | K6: =ROUND((G6/5)*60+MIN(MAX(J6/D6,0),0.6)*40,0) | L6: Sample product; compare dimensions and installation requirements.
A7: Portable LED Desk Lamp | B7: Lazada | C7: Lighting | D7: 24.99 | E7: 10 | F7: 0.12 | G7: 4.6 | H7: 1250 | I7: =D7*F7 | J7: =D7-E7-I7 | K7: =ROUND((G7/5)*60+MIN(MAX(J7/D7,0),0.6)*40,0) | L7: Sample product; confirm specs and safety certifications.
A8: Foldable Laptop Riser | B8: Amazon | C8: Desk Accessories | D8: 19.99 | E8: 7 | F8: 0.15 | G8: 4.2 | H8: 430 | I8: =D8*F8 | J8: =D8-E8-I8 | K8: =ROUND((G8/5)*60+MIN(MAX(J8/D8,0),0.6)*40,0) | L8: Sample product; compare materials and weight capacity.
A9: Minimalist Desk Organizer | B9: Shopee | C9: Office Organization | D9: 14.99 | E9: 4.5 | F9: 0.12 | G9: 4.1 | H9: 285 | I9: =D9*F9 | J9: =D9-E9-I9 | K9: =ROUND((G9/5)*60+MIN(MAX(J9/D9,0),0.6)*40,0) | L9: Sample product; verify dimensions and storage compartments.
A10: USB-C Hub Adapter | B10: Amazon | C10: Computer Accessories | D10: 34.99 | E10: 18 | F10: 0.15 | G10: 4.4 | H10: 2100 | I10: =D10*F10 | J10: =D10-E10-I10 | K10: =ROUND((G10/5)*60+MIN(MAX(J10/D10,0),0.6)*40,0) | L10: Sample product; verify ports, compatibility, and warranty.
A11: Ergonomic Footrest | B11: Lazada | C11: Office Comfort | D11: 27.99 | E11: 11.5 | F11: 0.12 | G11: 4.5 | H11: 790 | I11: =D11*F11 | J11: =D11-E11-I11 | K11: =ROUND((G11/5)*60+MIN(MAX(J11/D11,0),0.6)*40,0) | L11: Sample product; compare size, adjustability, and materials.
A13: Scoring note: | B13: The score is a simple illustrative formula combining rating and estimated gross margin; it is not a market-demand forecast.

Sheet 2 Listing Audit
A1: PROJECT 2 | PRODUCT LISTING QUALITY AUDIT
A2: A practical checklist for identifying missing or weak product listing information.
A3: SKU | B3: Product Name | C3: Title Present? | D3: Description Present? | E3: Images Checked? | F3: Price Checked? | G3: Category Correct? | H3: Key Attributes Complete? | I3: Listing Status | J3: Priority | K3: Recommended Action | L3: Owner/Notes
A4: DSK-001 | B4: Adjustable Laptop Stand | C4: Yes | D4: Yes | E4: Yes | F4: Yes | G4: Yes | H4: Yes | I4: =IF(COUNTIF(C4:H4,"No")>=3,"Needs Major Update",IF(COUNTIF(C4:H4,"No")>=1,"Needs Review","Ready for QA")) | J4: Low | K4: Maintain listing; schedule periodic price and stock checks. | L4: Sample record
A5: DSK-002 | B5: Under-Desk Headphone Hanger | C5: Yes | D5: Yes | E5: No | F5: Yes | G5: Yes | H5: No | I5: =IF(COUNTIF(C5:H5,"No")>=3,"Needs Major Update",IF(COUNTIF(C5:H5,"No")>=1,"Needs Review","Ready for QA")) | J5: High | K5: Review image set and fill missing compatibility/material details. | L5: Sample record
A6: ORG-003 | B6: Cable Management Tray | C6: Yes | D6: No | E6: Yes | F6: No | G6: Yes | H6: No | I6: =IF(COUNTIF(C6:H6,"No")>=3,"Needs Major Update",IF(COUNTIF(C6:H6,"No")>=1,"Needs Review","Ready for QA")) | J6: High | K6: Update description, verify current price, complete dimensions/material. | L6: Sample record
A7: LGT-004 | B7: Portable LED Desk Lamp | C7: Yes | D7: Yes | E7: Yes | F7: Yes | G7: No | H7: Yes | I7: =IF(COUNTIF(C7:H7,"No")>=3,"Needs Major Update",IF(COUNTIF(C7:H7,"No")>=1,"Needs Review","Ready for QA")) | J7: Medium | K7: Confirm the category matches the store taxonomy. | L7: Sample record
A8: DSK-005 | B8: Foldable Laptop Riser | C8: No | D8: Yes | E8: Yes | F8: Yes | G8: Yes | H8: No | I8: =IF(COUNTIF(C8:H8,"No")>=3,"Needs Major Update",IF(COUNTIF(C8:H8,"No")>=1,"Needs Review","Ready for QA")) | J8: High | K8: Write a clear title and complete the missing product attributes. | L8: Sample record
A9: ORG-006 | B9: Minimalist Desk Organizer | C9: Yes | D9: Yes | E9: Yes | F9: No | G9: Yes | H9: Yes | I9: =IF(COUNTIF(C9:H9,"No")>=3,"Needs Major Update",IF(COUNTIF(C9:H9,"No")>=1,"Needs Review","Ready for QA")) | J9: Medium | K9: Verify price against approved source before publishing. | L9: Sample record
A10: TEC-007 | B10: USB-C Hub Adapter | C10: Yes | D10: Yes | E10: No | F10: Yes | G10: Yes | H10: No | I10: =IF(COUNTIF(C10:H10,"No")>=3,"Needs Major Update",IF(COUNTIF(C10:H10,"No")>=1,"Needs Review","Ready for QA")) | J10: High | K10: Check image quality and list compatible devices/ports accurately. | L10: Sample record
A11: COM-008 | B11: Ergonomic Footrest | C11: Yes | D11: Yes | E11: Yes | F11: Yes | G11: Yes | H11: Yes | I11: =IF(COUNTIF(C11:H11,"No")>=3,"Needs Major Update",IF(COUNTIF(C11:H11,"No")>=1,"Needs Review","Ready for QA")) | J11: Low | K11: Maintain listing; confirm claims are supported by product specs. | L11: Sample record

Sheet 3 Inventory Tracker
A1: PROJECT 3 | INVENTORY & REORDER TRACKER
A2: Change stock, sales, lead time, or safety stock to see reorder alerts and suggested order quantities.
A3: SKU | B3: Product | C3: Supplier | D3: Stock On Hand | E3: Avg Daily Sales | F3: Lead Time (Days) | G3: Safety Stock | H3: Reorder Point | I3: Suggested Order Qty | J3: Stock Status | K3: Unit Cost (USD) | L3: Stock Value (USD) | M3: Notes
A4: DSK-001 | B4: Adjustable Laptop Stand | C4: Supplier A | D4: 42 | E4: 3.2 | F4: 7 | G4: 10 | H4: =ROUND(E4*F4+G4,0) | I4: =MAX(0,ROUNDUP(H4-D4+E4*14,0)) | J4: =IF(D4<=H4,"REORDER","In Stock") | K4: 12 | L4: =D4*K4 | M4: Fictional sample
A5: DSK-002 | B5: Under-Desk Headphone Hanger | C5: Supplier B | D5: 18 | E5: 4 | F5: 5 | G5: 8 | H5: =ROUND(E5*F5+G5,0) | I5: =MAX(0,ROUNDUP(H5-D5+E5*14,0)) | J5: =IF(D5<=H5,"REORDER","In Stock") | K5: 5.5 | L5: =D5*K5 | M5: Fictional sample
A6: ORG-003 | B6: Cable Management Tray | C6: Supplier C | D6: 9 | E6: 1.8 | F6: 10 | G6: 6 | H6: =ROUND(E6*F6+G6,0) | I6: =MAX(0,ROUNDUP(H6-D6+E6*14,0)) | J6: =IF(D6<=H6,"REORDER","In Stock") | K6: 8.25 | L6: =D6*K6 | M6: Fictional sample
A7: LGT-004 | B7: Portable LED Desk Lamp | C7: Supplier A | D7: 30 | E7: 2.4 | F7: 8 | G7: 8 | H7: =ROUND(E7*F7+G7,0) | I7: =MAX(0,ROUNDUP(H7-D7+E7*14,0)) | J7: =IF(D7<=H7,"REORDER","In Stock") | K7: 10 | L7: =D7*K7 | M7: Fictional sample
A8: DSK-005 | B8: Foldable Laptop Riser | C8: Supplier B | D8: 7 | E8: 1.6 | F8: 6 | G8: 5 | H8: =ROUND(E8*F8+G8,0) | I8: =MAX(0,ROUNDUP(H8-D8+E8*14,0)) | J8: =IF(D8<=H8,"REORDER","In Stock") | K8: 7 | L8: =D8*K8 | M8: Fictional sample
A9: ORG-006 | B9: Minimalist Desk Organizer | C9: Supplier C | D9: 25 | E9: 2 | F9: 9 | G9: 7 | H9: =ROUND(E9*F9+G9,0) | I9: =MAX(0,ROUNDUP(H9-D9+E9*14,0)) | J9: =IF(D9<=H9,"REORDER","In Stock") | K9: 4.5 | L9: =D9*K9 | M9: Fictional sample
A10: TEC-007 | B10: USB-C Hub Adapter | C10: Supplier D | D10: 12 | E10: 1.5 | F10: 12 | G10: 8 | H10: =ROUND(E10*F10+G10,0) | I10: =MAX(0,ROUNDUP(H10-D10+E10*14,0)) | J10: =IF(D10<=H10,"REORDER","In Stock") | K10: 18 | L10: =D10*K10 | M10: Fictional sample
A11: COM-008 | B11: Ergonomic Footrest | C11: Supplier A | D11: 16 | E11: 1.1 | F11: 10 | G11: 5 | H11: =ROUND(E11*F11+G11,0) | I11: =MAX(0,ROUNDUP(H11-D11+E11*14,0)) | J11: =IF(D11<=H11,"REORDER","In Stock") | K11: 11.5 | L11: =D11*K11 | M11: Fictional sample
A13: Formula assumptions: | B13: Reorder point = average daily sales × lead time + safety stock. Suggested order qty targets about 14 days of additional coverage; adjust this rule to the store's policy.

Sheet 4 Order Tracker
A1: PROJECT 4 | ORDER OPERATIONS TRACKER
A2: Sample order queue for tracking payment, fulfillment, and follow-up needs.
A3: Order ID | B3: Order Date | C3: Channel | D3: Customer Ref | E3: SKU | F3: Qty | G3: Order Value (USD) | H3: Payment Status | I3: Fulfillment Status | J3: Days Since Order | K3: Follow-up Flag | L3: Issue / Next Action
A4: ORD-1001 | B4: 2026-10-02 | C4: Website | D4: Customer A | E4: DSK-001 | F4: 1 | G4: 29.99 | H4: Paid | I4: Shipped | J4: =DATE(2026,10,14)-DATEVALUE(B4) | K4: =IF(OR(H4="Pending",I4="On Hold",AND(I4="Processing",J4>=2)),"FOLLOW UP","No immediate action") | L4: Send tracking update if needed.
A5: ORD-1002 | B5: 2026-10-03 | C5: Amazon | D5: Customer B | E5: DSK-002 | F5: 2 | G5: 33.98 | H5: Paid | I5: Processing | J5: =DATE(2026,10,14)-DATEVALUE(B5) | K5: =IF(OR(H5="Pending",I5="On Hold",AND(I5="Processing",J5>=2)),"FOLLOW UP","No immediate action") | L5: Check fulfillment queue.
A6: ORD-1003 | B6: 2026-10-04 | C6: Shopee | D6: Customer C | E6: ORG-003 | F6: 1 | G6: 22.5 | H6: Pending | I6: On Hold | J6: =DATE(2026,10,14)-DATEVALUE(B6) | K6: =IF(OR(H6="Pending",I6="On Hold",AND(I6="Processing",J6>=2)),"FOLLOW UP","No immediate action") | L6: Confirm payment before processing.
A7: ORD-1004 | B7: 2026-10-05 | C7: Lazada | D7: Customer D | E7: LGT-004 | F7: 1 | G7: 24.99 | H7: Paid | I7: Delivered | J7: =DATE(2026,10,14)-DATEVALUE(B7) | K7: =IF(OR(H7="Pending",I7="On Hold",AND(I7="Processing",J7>=2)),"FOLLOW UP","No immediate action") | L7: No action unless customer raises an issue.
A8: ORD-1005 | B8: 2026-10-06 | C8: Website | D8: Customer E | E8: DSK-005 | F8: 3 | G8: 59.97 | H8: Paid | I8: Processing | J8: =DATE(2026,10,14)-DATEVALUE(B8) | K8: =IF(OR(H8="Pending",I8="On Hold",AND(I8="Processing",J8>=2)),"FOLLOW UP","No immediate action") | L8: Confirm stock availability.
A9: ORD-1006 | B9: 2026-10-07 | C9: Amazon | D9: Customer F | E9: TEC-007 | F9: 1 | G9: 34.99 | H9: Refunded | I9: Cancelled | J9: =DATE(2026,10,14)-DATEVALUE(B9) | K9: =IF(OR(H9="Pending",I9="On Hold",AND(I9="Processing",J9>=2)),"FOLLOW UP","No immediate action") | L9: Check refund completion record.
A10: ORD-1007 | B10: 2026-10-08 | C10: Shopee | D10: Customer G | E10: COM-008 | F10: 2 | G10: 55.98 | H10: Paid | I10: Shipped | J10: =DATE(2026,10,14)-DATEVALUE(B10) | K10: =IF(OR(H10="Pending",I10="On Hold",AND(I10="Processing",J10>=2)),"FOLLOW UP","No immediate action") | L10: Monitor delivery status.
A11: ORD-1008 | B11: 2026-10-09 | C11: Website | D11: Customer H | E11: ORG-006 | F11: 1 | G11: 14.99 | H11: Pending | I11: Processing | J11: =DATE(2026,10,14)-DATEVALUE(B11) | K11: =IF(OR(H11="Pending",I11="On Hold",AND(I11="Processing",J11>=2)),"FOLLOW UP","No immediate action") | L11: Resolve payment status before dispatch.
